django_admin_groups/__init__.py
django_admin_groups/admin.py
django_admin_groups/apps.py
django_admin_groups/context_processors.py
django_admin_groups/templates/admin/app_index.html
django_admin_groups/templates/admin/base.html
django_admin_groups/templates/admin/change_form.html
django_admin_groups/templates/admin/change_list.html
django_admin_groups/templates/admin/delete_confirmation.html
django_admin_groups/templates/admin/delete_selected_confirmation.html
django_admin_groups/templates/admin/invalid_setup.html
django_admin_groups/templates/admin/object_history.html
django_admin_groups/templates/django_admin_groups/breadcrumbs.html
django_admin_groups/templatetags/__init__.py
django_admin_groups/templatetags/custom_filters.py
django_admin_groups/templatetags/__pycache__/custom_filters.cpython-312.pyc
django_admin_groups-1.0.1.dist-info/licenses/LICENSE
tests/__init__.py
tests/test_admin.py
django_admin_groups-1.0.1.dist-info/METADATA
django_admin_groups-1.0.1.dist-info/WHEEL
django_admin_groups-1.0.1.dist-info/top_level.txt
django_admin_groups-1.0.1.dist-info/RECORD
